pyrdui/__init__.py
pyrdui/action.py
pyrdui/button.py
pyrdui/datatable.py
pyrdui/date.py
pyrdui/download.py
pyrdui/file.py
pyrdui/image.py
pyrdui/layout.py
pyrdui/select.py
pyrdui/stream.py
pyrdui/text.py
pyrdui/video.py
pyrdui-1.0.1.dist-info/LICENSE
pyrdui-1.0.1.dist-info/METADATA
pyrdui-1.0.1.dist-info/WHEEL
pyrdui-1.0.1.dist-info/top_level.txt
pyrdui-1.0.1.dist-info/RECORD
