Metadata-Version: 2.1
Name: pyrdui
Version: 1.0.1
Summary: reshape data UI library in py language 
Home-page: http://www.reshapedata.com
Author: Reshapedata
Author-email: hulilei@takewiki.com.cn
License: Apache License
Keywords: reshapedata,rdui,pyrdui
Platform: UNKNOWN
Requires-Python: >=3.6
Requires-Dist: requests
